graph_algorithms/__init__.py
graph_algorithms/tests.py
graph_algorithms-0.1.1.dist-info/METADATA
graph_algorithms-0.1.1.dist-info/WHEEL
graph_algorithms-0.1.1.dist-info/top_level.txt
graph_algorithms-0.1.1.dist-info/RECORD
