Metadata-Version: 2.1
Name: graph-algorithms
Version: 0.1.1
Summary: Common Graph Algorithms Library
Home-page: https://pypi.python.org/pypi/common_algorithms
Author: David McDougall <dam1784[at]rit.edu>
Author-email: dam1784@rit.edu
License: The MIT License (MIT)
Provides-Extra: debug
Requires-Dist: numpy ; extra == 'debug'
Provides-Extra: test
Requires-Dist: numpy ; extra == 'test'
